pandas_intervals/__init__.py
pandas_intervals/core.py
pandas_intervals/ops/__init__.py
pandas_intervals/ops/basic/__init__.py
pandas_intervals/ops/basic/combine.py
pandas_intervals/ops/basic/complement.py
pandas_intervals/ops/basic/intersection.py
pandas_intervals/ops/basic/nearest.py
pandas_intervals/ops/basic/overlap.py
pandas_intervals/ops/basic/truncate.py
pandas_intervals/ops/combine.py
pandas_intervals/ops/complement.py
pandas_intervals/ops/intersection.py
pandas_intervals/ops/nearest.py
pandas_intervals/ops/overlap.py
pandas_intervals/ops/truncate.py
pandas_intervals/utils.py
pandas_intervals/vis.py
pandas_intervals-1.0.1.dist-info/LICENSE
pandas_intervals-1.0.1.dist-info/METADATA
pandas_intervals-1.0.1.dist-info/WHEEL
pandas_intervals-1.0.1.dist-info/RECORD
