Metadata-Version: 2.1
Name: pandas-intervals
Version: 1.0.1
Summary: Pandas extention for Dataframes of intervals
License: GPL-v3.0
Author: BlakeJC94
Author-email: blakejamescook@gmail.com
Requires-Python: >=3.9,<4.0
Classifier: License :: Other/Proprietary License
Classifier: Programming Language :: Python :: 3
Classifier: Programming Language :: Python :: 3.9
Classifier: Programming Language :: Python :: 3.10
Classifier: Programming Language :: Python :: 3.11
Requires-Dist: numpy (==1.24.2)
Requires-Dist: pandas (<=1.6.3)
Requires-Dist: plotly (>=5.16.0,<6.0.0)
